LICENSE
README.md
setup.py
flyerapi/__init__.py
flyerapi/flyerapi.py
flyerapi.egg-info/PKG-INFO
flyerapi.egg-info/SOURCES.txt
flyerapi.egg-info/dependency_links.txt
flyerapi.egg-info/requires.txt
flyerapi.egg-info/top_level.txt