Metadata-Version: 2.1
Name: flyerapi
Version: 1.2.3
Summary: Asynchronous api of the Flyer service
Home-page: https://github.com/EliCreator/flyerapi
Author: Eli
Author-email: <eli.dev.tg@gmail.com>
Project-URL: Homepage, https://github.com/EliCreator/flyerapi
Project-URL: Bug Tracker, https://github.com/EliCreator/flyerapi/issues
Keywords: python,flyer,async,asyncio,cache
Classifier: Development Status :: 4 - Beta
Classifier: Intended Audience :: Developers
Classifier: Programming Language :: Python :: 3
Classifier: Operating System :: Unix
Classifier: Operating System :: MacOS :: MacOS X
Classifier: Operating System :: Microsoft :: Windows
License-File: LICENSE
